{
  "title": "McDonald's Collection (2012) Set",
  "link": "/McDonalds-Collection-2012-Expansion/",
  "logo": "https://den-media.pokellector.com/logos/McDonalds-Promos-2012.logo.11.png",
  "symbol": "https://den-media.pokellector.com/logos/McDonalds-Promos-2012.symbol.11.png",
  "scraped": true,
  "cards": {
    "1": {
      "number": "1",
      "name": "Servine",
      "title": "Servine - McDonald's Collection (2012) #1",
      "link": "/McDonalds-Collection-2012-Expansion/Servine-Card-1",
      "image": "https://den-cards.pokellector.com/11/Servine.MCD.1.thumb.png",
      "full_image": "https://den-cards.pokellector.com/11/Servine.MCD.1.png",
      "details_scraped": true,
      "rarity": "Common",
      "set_name": "McDonald's Collection (2012)",
      "set_link": "/McDonalds-Collection-2012-Expansion/",
      "position": "1/12",
      "card_number": "1",
      "total_cards": "12",
      "image_full": "https://den-cards.pokellector.com/11/Servine.MCD.1.png",
      "prices": [
        {
          "vendor": "TCG Player",
          "price": "$1.78",
          "link": "https://partner.tcgplayer.com/c/2698352/1830156/21018?u=https%3A%2F%2Fstore.tcgplayer.com%2Fpokemon%2Fmcdonalds-promos-2012%2Fservine"
        },
        {
          "vendor": "Troll & Toad",
          "price": "$5.39",
          "link": "http://www.trollandtoad.com/p386287.html"
        },
        {
          "vendor": "eBay",
          "price": "$3.95",
          "link": "https://www.ebay.com/sch/i.html?_from=R40&_nkw=Servine+Mcdonalds+Promo+1&mkcid=1&mkrid=711-53200-19255-0&siteid=0&campid=5337432989&customid=&toolid=10001&mkevt=1"
        }
      ],
      "alternate_versions": []
    },
    "2": {
      "number": "2",
      "name": "Pansage",
      "title": "Pansage - McDonald's Collection (2012) #2",
      "link": "/McDonalds-Collection-2012-Expansion/Pansage-Card-2",
      "image": "https://den-cards.pokellector.com/11/Pansage.MCD.2.thumb.png",
      "full_image": "https://den-cards.pokellector.com/11/Pansage.MCD.2.png",
      "details_scraped": true,
      "rarity": "Common",
      "set_name": "McDonald's Collection (2012)",
      "set_link": "/McDonalds-Collection-2012-Expansion/",
      "position": "2/12",
      "card_number": "2",
      "total_cards": "12",
      "image_full": "https://den-cards.pokellector.com/11/Pansage.MCD.2.png",
      "prices": [
        {
          "vendor": "TCG Player",
          "price": "$2.39",
          "link": "https://partner.tcgplayer.com/c/2698352/1830156/21018?u=https%3A%2F%2Fstore.tcgplayer.com%2Fpokemon%2Fmcdonalds-promos-2012%2Fpansage"
        },
        {
          "vendor": "Troll & Toad",
          "price": "$3.49",
          "link": "http://www.trollandtoad.com/p386288.html"
        },
        {
          "vendor": "eBay",
          "price": "$2.99",
          "link": "https://www.ebay.com/sch/i.html?_from=R40&_nkw=Pansage+Mcdonalds+Promo+2&mkcid=1&mkrid=711-53200-19255-0&siteid=0&campid=5337432989&customid=&toolid=10001&mkevt=1"
        }
      ],
      "alternate_versions": []
    },
    "3": {
      "number": "3",
      "name": "Dwebble",
      "title": "Dwebble - McDonald's Collection (2012) #3",
      "link": "/McDonalds-Collection-2012-Expansion/Dwebble-Card-3",
      "image": "https://den-cards.pokellector.com/11/Dwebble.MCD.3.thumb.png",
      "full_image": "https://den-cards.pokellector.com/11/Dwebble.MCD.3.png",
      "details_scraped": true,
      "rarity": "Common",
      "set_name": "McDonald's Collection (2012)",
      "set_link": "/McDonalds-Collection-2012-Expansion/",
      "position": "3/12",
      "card_number": "3",
      "total_cards": "12",
      "image_full": "https://den-cards.pokellector.com/11/Dwebble.MCD.3.png",
      "prices": [
        {
          "vendor": "TCG Player",
          "price": "$2.21",
          "link": "https://partner.tcgplayer.com/c/2698352/1830156/21018?u=https%3A%2F%2Fstore.tcgplayer.com%2Fpokemon%2Fmcdonalds-promos-2012%2Fdwebble"
        },
        {
          "vendor": "Troll & Toad",
          "price": "$4.39",
          "link": "http://www.trollandtoad.com/p386289.html"
        },
        {
          "vendor": "eBay",
          "price": "$2.90",
          "link": "https://www.ebay.com/sch/i.html?_from=R40&_nkw=Dwebble+Mcdonalds+Promo+3&mkcid=1&mkrid=711-53200-19255-0&siteid=0&campid=5337432989&customid=&toolid=10001&mkevt=1"
        }
      ],
      "alternate_versions": []
    },
    "4": {
      "number": "4",
      "name": "Pignite",
      "title": "Pignite - McDonald's Collection (2012) #4",
      "link": "/McDonalds-Collection-2012-Expansion/Pignite-Card-4",
      "image": "https://den-cards.pokellector.com/11/Pignite.MCD.4.thumb.png",
      "full_image": "https://den-cards.pokellector.com/11/Pignite.MCD.4.png",
      "details_scraped": true,
      "rarity": "Common",
      "set_name": "McDonald's Collection (2012)",
      "set_link": "/McDonalds-Collection-2012-Expansion/",
      "position": "4/12",
      "card_number": "4",
      "total_cards": "12",
      "image_full": "https://den-cards.pokellector.com/11/Pignite.MCD.4.png",
      "prices": [
        {
          "vendor": "TCG Player",
          "price": "$4.67",
          "link": "https://partner.tcgplayer.com/c/2698352/1830156/21018?u=https%3A%2F%2Fstore.tcgplayer.com%2Fpokemon%2Fmcdonalds-promos-2012%2Fpignite"
        },
        {
          "vendor": "Troll & Toad",
          "price": "$6.99",
          "link": "http://www.trollandtoad.com/p386290.html"
        },
        {
          "vendor": "eBay",
          "price": "$4.99",
          "link": "https://www.ebay.com/sch/i.html?_from=R40&_nkw=Pignite+Mcdonalds+Promo+4&mkcid=1&mkrid=711-53200-19255-0&siteid=0&campid=5337432989&customid=&toolid=10001&mkevt=1"
        }
      ],
      "alternate_versions": []
    },
    "5": {
      "number": "5",
      "name": "Dewott",
      "title": "Dewott - McDonald's Collection (2012) #5",
      "link": "/McDonalds-Collection-2012-Expansion/Dewott-Card-5",
      "image": "https://den-cards.pokellector.com/11/Dewott.MCD.5.thumb.png",
      "full_image": "https://den-cards.pokellector.com/11/Dewott.MCD.5.png",
      "details_scraped": true,
      "rarity": "Common",
      "set_name": "McDonald's Collection (2012)",
      "set_link": "/McDonalds-Collection-2012-Expansion/",
      "position": "5/12",
      "card_number": "5",
      "total_cards": "12",
      "image_full": "https://den-cards.pokellector.com/11/Dewott.MCD.5.png",
      "prices": [
        {
          "vendor": "TCG Player",
          "price": "$3.42",
          "link": "https://partner.tcgplayer.com/c/2698352/1830156/21018?u=https%3A%2F%2Fstore.tcgplayer.com%2Fpokemon%2Fmcdonalds-promos-2012%2Fdewott"
        },
        {
          "vendor": "Troll & Toad",
          "price": "$7.99",
          "link": "http://www.trollandtoad.com/p386291.html"
        },
        {
          "vendor": "eBay",
          "price": "$4.75",
          "link": "https://www.ebay.com/sch/i.html?_from=R40&_nkw=Dewott+Mcdonalds+Promo+5&mkcid=1&mkrid=711-53200-19255-0&siteid=0&campid=5337432989&customid=&toolid=10001&mkevt=1"
        }
      ],
      "alternate_versions": []
    },
    "6": {
      "number": "6",
      "name": "Emolga",
      "title": "Emolga - McDonald's Collection (2012) #6",
      "link": "/McDonalds-Collection-2012-Expansion/Emolga-Card-6",
      "image": "https://den-cards.pokellector.com/11/Emolga.MCD.6.thumb.png",
      "full_image": "https://den-cards.pokellector.com/11/Emolga.MCD.6.png",
      "details_scraped": true,
      "rarity": "Common",
      "set_name": "McDonald's Collection (2012)",
      "set_link": "/McDonalds-Collection-2012-Expansion/",
      "position": "6/12",
      "card_number": "6",
      "total_cards": "12",
      "image_full": "https://den-cards.pokellector.com/11/Emolga.MCD.6.png",
      "prices": [
        {
          "vendor": "TCG Player",
          "price": "$5.95",
          "link": "https://partner.tcgplayer.com/c/2698352/1830156/21018?u=https%3A%2F%2Fstore.tcgplayer.com%2Fpokemon%2Fmcdonalds-promos-2012%2Femolga"
        },
        {
          "vendor": "Troll & Toad",
          "price": "$6.99",
          "link": "http://www.trollandtoad.com/p386292.html"
        },
        {
          "vendor": "eBay",
          "price": "$2.99",
          "link": "https://www.ebay.com/sch/i.html?_from=R40&_nkw=Emolga+Mcdonalds+Promo+6&mkcid=1&mkrid=711-53200-19255-0&siteid=0&campid=5337432989&customid=&toolid=10001&mkevt=1"
        }
      ],
      "alternate_versions": []
    },
    "7": {
      "number": "7",
      "name": "Woobat",
      "title": "Woobat - McDonald's Collection (2012) #7",
      "link": "/McDonalds-Collection-2012-Expansion/Woobat-Card-7",
      "image": "https://den-cards.pokellector.com/11/Woobat.MCD.7.thumb.png",
      "full_image": "https://den-cards.pokellector.com/11/Woobat.MCD.7.png",
      "details_scraped": true,
      "rarity": "Common",
      "set_name": "McDonald's Collection (2012)",
      "set_link": "/McDonalds-Collection-2012-Expansion/",
      "position": "7/12",
      "card_number": "7",
      "total_cards": "12",
      "image_full": "https://den-cards.pokellector.com/11/Woobat.MCD.7.png",
      "prices": [
        {
          "vendor": "TCG Player",
          "price": "$7.00",
          "link": "https://partner.tcgplayer.com/c/2698352/1830156/21018?u=https%3A%2F%2Fstore.tcgplayer.com%2Fpokemon%2Fmcdonalds-promos-2012%2Fwoobat"
        },
        {
          "vendor": "Troll & Toad",
          "price": "$2.49",
          "link": "http://www.trollandtoad.com/p386293.html"
        },
        {
          "vendor": "eBay",
          "price": "$1.89",
          "link": "https://www.ebay.com/sch/i.html?_from=R40&_nkw=Woobat+Mcdonalds+Promo+7&mkcid=1&mkrid=711-53200-19255-0&siteid=0&campid=5337432989&customid=&toolid=10001&mkevt=1"
        }
      ],
      "alternate_versions": []
    },
    "8": {
      "number": "8",
      "name": "Drilbur",
      "title": "Drilbur - McDonald's Collection (2012) #8",
      "link": "/McDonalds-Collection-2012-Expansion/Drilbur-Card-8",
      "image": "https://den-cards.pokellector.com/11/Drilbur.MCD.8.thumb.png",
      "full_image": "https://den-cards.pokellector.com/11/Drilbur.MCD.8.png",
      "details_scraped": true,
      "rarity": "Common",
      "set_name": "McDonald's Collection (2012)",
      "set_link": "/McDonalds-Collection-2012-Expansion/",
      "position": "8/12",
      "card_number": "8",
      "total_cards": "12",
      "image_full": "https://den-cards.pokellector.com/11/Drilbur.MCD.8.png",
      "prices": [
        {
          "vendor": "TCG Player",
          "price": "$2.00",
          "link": "https://partner.tcgplayer.com/c/2698352/1830156/21018?u=https%3A%2F%2Fstore.tcgplayer.com%2Fpokemon%2Fmcdonalds-promos-2012%2Fdrilbur"
        },
        {
          "vendor": "Troll & Toad",
          "price": "$9.99",
          "link": "http://www.trollandtoad.com/p386294.html"
        },
        {
          "vendor": "eBay",
          "price": "$2.60",
          "link": "https://www.ebay.com/sch/i.html?_from=R40&_nkw=Drilbur+Mcdonalds+Promo+8&mkcid=1&mkrid=711-53200-19255-0&siteid=0&campid=5337432989&customid=&toolid=10001&mkevt=1"
        }
      ],
      "alternate_versions": []
    },
    "9": {
      "number": "9",
      "name": "Purrloin",
      "title": "Purrloin - McDonald's Collection (2012) #9",
      "link": "/McDonalds-Collection-2012-Expansion/Purrloin-Card-9",
      "image": "https://den-cards.pokellector.com/11/Purrloin.MCD.9.thumb.png",
      "full_image": "https://den-cards.pokellector.com/11/Purrloin.MCD.9.png",
      "details_scraped": true,
      "rarity": "Common",
      "set_name": "McDonald's Collection (2012)",
      "set_link": "/McDonalds-Collection-2012-Expansion/",
      "position": "9/12",
      "card_number": "9",
      "total_cards": "12",
      "image_full": "https://den-cards.pokellector.com/11/Purrloin.MCD.9.png",
      "prices": [
        {
          "vendor": "TCG Player",
          "price": "$8.00",
          "link": "https://partner.tcgplayer.com/c/2698352/1830156/21018?u=https%3A%2F%2Fstore.tcgplayer.com%2Fpokemon%2Fmcdonalds-promos-2012%2Fpurrloin"
        },
        {
          "vendor": "Troll & Toad",
          "price": "$5.19",
          "link": "http://www.trollandtoad.com/p386295.html"
        },
        {
          "vendor": "eBay",
          "price": "$1.49",
          "link": "https://www.ebay.com/sch/i.html?_from=R40&_nkw=Purrloin+Mcdonalds+Promo+9&mkcid=1&mkrid=711-53200-19255-0&siteid=0&campid=5337432989&customid=&toolid=10001&mkevt=1"
        }
      ],
      "alternate_versions": []
    },
    "10": {
      "number": "10",
      "name": "Scraggy",
      "title": "Scraggy - McDonald's Collection (2012) #10",
      "link": "/McDonalds-Collection-2012-Expansion/Scraggy-Card-10",
      "image": "https://den-cards.pokellector.com/11/Scraggy.MCD.10.thumb.png",
      "full_image": "https://den-cards.pokellector.com/11/Scraggy.MCD.10.png",
      "details_scraped": true,
      "rarity": "Common",
      "set_name": "McDonald's Collection (2012)",
      "set_link": "/McDonalds-Collection-2012-Expansion/",
      "position": "10/12",
      "card_number": "10",
      "total_cards": "12",
      "image_full": "https://den-cards.pokellector.com/11/Scraggy.MCD.10.png",
      "prices": [
        {
          "vendor": "TCG Player",
          "price": "$4.66",
          "link": "https://partner.tcgplayer.com/c/2698352/1830156/21018?u=https%3A%2F%2Fstore.tcgplayer.com%2Fpokemon%2Fmcdonalds-promos-2012%2Fscraggy"
        },
        {
          "vendor": "Troll & Toad",
          "price": "$2.99",
          "link": "http://www.trollandtoad.com/p386296.html"
        },
        {
          "vendor": "eBay",
          "price": "$3.99",
          "link": "https://www.ebay.com/sch/i.html?_from=R40&_nkw=Scraggy+Mcdonalds+Promo+10&mkcid=1&mkrid=711-53200-19255-0&siteid=0&campid=5337432989&customid=&toolid=10001&mkevt=1"
        }
      ],
      "alternate_versions": []
    },
    "11": {
      "number": "11",
      "name": "Klang",
      "title": "Klang - McDonald's Collection (2012) #11",
      "link": "/McDonalds-Collection-2012-Expansion/Klang-Card-11",
      "image": "https://den-cards.pokellector.com/11/Klang.MCD.11.thumb.png",
      "full_image": "https://den-cards.pokellector.com/11/Klang.MCD.11.png",
      "details_scraped": true,
      "rarity": "Common",
      "set_name": "McDonald's Collection (2012)",
      "set_link": "/McDonalds-Collection-2012-Expansion/",
      "position": "11/12",
      "card_number": "11",
      "total_cards": "12",
      "image_full": "https://den-cards.pokellector.com/11/Klang.MCD.11.png",
      "prices": [
        {
          "vendor": "TCG Player",
          "price": "$1.44",
          "link": "https://partner.tcgplayer.com/c/2698352/1830156/21018?u=https%3A%2F%2Fstore.tcgplayer.com%2Fpokemon%2Fmcdonalds-promos-2012%2Fklang"
        },
        {
          "vendor": "Troll & Toad",
          "price": "$3.99",
          "link": "http://www.trollandtoad.com/p386297.html"
        },
        {
          "vendor": "eBay",
          "price": "$2.67",
          "link": "https://www.ebay.com/sch/i.html?_from=R40&_nkw=Klang+Mcdonalds+Promo+11&mkcid=1&mkrid=711-53200-19255-0&siteid=0&campid=5337432989&customid=&toolid=10001&mkevt=1"
        }
      ],
      "alternate_versions": []
    },
    "12": {
      "number": "12",
      "name": "Axew",
      "title": "Axew - McDonald's Collection (2012) #12",
      "link": "/McDonalds-Collection-2012-Expansion/Axew-Card-12",
      "image": "https://den-cards.pokellector.com/11/Axew.MCD.12.thumb.png",
      "full_image": "https://den-cards.pokellector.com/11/Axew.MCD.12.png",
      "details_scraped": true,
      "rarity": "Common",
      "set_name": "McDonald's Collection (2012)",
      "set_link": "/McDonalds-Collection-2012-Expansion/",
      "position": "12/12",
      "card_number": "12",
      "total_cards": "12",
      "image_full": "https://den-cards.pokellector.com/11/Axew.MCD.12.png",
      "prices": [
        {
          "vendor": "TCG Player",
          "price": "$2.57",
          "link": "https://partner.tcgplayer.com/c/2698352/1830156/21018?u=https%3A%2F%2Fstore.tcgplayer.com%2Fpokemon%2Fmcdonalds-promos-2012%2Faxew"
        },
        {
          "vendor": "Troll & Toad",
          "price": "$4.59",
          "link": "http://www.trollandtoad.com/p386298.html"
        },
        {
          "vendor": "eBay",
          "price": "$2.00",
          "link": "https://www.ebay.com/sch/i.html?_from=R40&_nkw=Axew+Mcdonalds+Promo+12&mkcid=1&mkrid=711-53200-19255-0&siteid=0&campid=5337432989&customid=&toolid=10001&mkevt=1"
        }
      ],
      "alternate_versions": []
    }
  },
  "scraped_date": "2026-03-28 08:39:49"
}